aiida_plumed/__init__.py
aiida_plumed/__init__.pyc
aiida_plumed/calculations.py
aiida_plumed/cli.py
aiida_plumed/cli.pyc
aiida_plumed/helpers.py
aiida_plumed/helpers.pyc
aiida_plumed/parsers.py
aiida_plumed/calculations/__init__.py
aiida_plumed/calculations/__init__.pyc
aiida_plumed/calculations/calculations.py
aiida_plumed/calculations/test.py
aiida_plumed/data/__init__.py
aiida_plumed/data/__init__.pyc
aiida_plumed/data/data_cli.py
aiida_plumed/tests/__init__.py
aiida_plumed/tests/__init__.pyc
aiida_plumed/tests/file1.txt
aiida_plumed/tests/file2.txt
aiida_plumed/tests/test_calculations.py
aiida_plumed/tests/test_cli.py
aiida_plumed/tests/input_files/__init__.py
aiida_plumed/tests/input_files/file1.txt
aiida_plumed/tests/input_files/file2.txt
aiida_plumed-0.1.0a0.dist-info/LICENSE
aiida_plumed-0.1.0a0.dist-info/METADATA
aiida_plumed-0.1.0a0.dist-info/WHEEL
aiida_plumed-0.1.0a0.dist-info/entry_points.txt
aiida_plumed-0.1.0a0.dist-info/top_level.txt
aiida_plumed-0.1.0a0.dist-info/RECORD
