Metadata-Version: 2.1
Name: aiida-plumed
Version: 0.1.0a0
Summary: AiiDA plugin providing support for Plumed2
Home-page: https://github.com/ConradJohnston/aiida-plumed
Author: Conrad Johnston
Author-email: conrad.s.johnston@googlemail.com
License: MIT
Platform: UNKNOWN
Classifier: Programming Language :: Python
Classifier: Intended Audience :: Science/Research
Classifier: License :: OSI Approved :: MIT License
Classifier: Natural Language :: English
Classifier: Framework :: AiiDA
Classifier: Development Status :: 2 - Pre-Alpha
Requires-Dist: aiida-core (<2.0.0,>=1.0.0b3)
Requires-Dist: six
Requires-Dist: voluptuous
Provides-Extra: docs
Requires-Dist: sphinx ; extra == 'docs'
Provides-Extra: pre-commit
Requires-Dist: pre-commit (==1.11.0) ; extra == 'pre-commit'
Requires-Dist: yapf (==0.27.0) ; extra == 'pre-commit'
Requires-Dist: prospector (==0.12.11) ; extra == 'pre-commit'
Requires-Dist: pylint (==1.9.4) ; extra == 'pre-commit'
Provides-Extra: testing
Requires-Dist: pgtest (==1.2.0) ; extra == 'testing'
Requires-Dist: wheel (>=0.31) ; extra == 'testing'
Requires-Dist: coverage ; extra == 'testing'
Requires-Dist: pytest (<5.0.0,>=3.6.3) ; extra == 'testing'
Requires-Dist: pytest-cov (<5.0.0,>=2.6.1) ; extra == 'testing'
